eot/__init__.py
eot/__main__.py
eot/eot.py
eot-0.1.1.dist-info/METADATA
eot-0.1.1.dist-info/WHEEL
eot-0.1.1.dist-info/entry_points.txt
eot-0.1.1.dist-info/top_level.txt
eot-0.1.1.dist-info/RECORD
