Metadata-Version: 2.1
Name: eot
Version: 0.1.1
Summary: Eons Official Time
Home-page: https://github.com/eons-dev/bin_eot
Author: eons
Author-email: support@eons.llc
Project-URL: Bug Tracker, https://github.com/eons-dev/bin_eot/issues
Classifier: Programming Language :: Python :: 3
Classifier: License :: OSI Approved :: MIT License
Classifier: Operating System :: OS Independent
Classifier: Development Status :: 4 - Beta
Requires-Python: >=3.7
